tuichat/__init__.py
tuichat/__main__.py
tuichat/client.py
tuichat/config.json
tuichat/log.txt
tuichat/server.py
tuichat/tuichat_utils/__init__.py
tuichat/tuichat_utils/data_handler.py
tuichat/tuichat_utils/exceptions.py
tuichat/tuichat_utils/ui.py
tuichat/tuichat_utils/__pycache__/__init__.cpython-37.pyc
tuichat/tuichat_utils/__pycache__/ui.cpython-37.pyc
tuichat/tuichat_utils/tui_elements/__init__.py
tuichat/tuichat_utils/tui_elements/block_symbols.json
tuichat/tuichat_utils/tui_elements/client_logo.txt
tuichat/tuichat_utils/tui_elements/copyright.txt
tuichat/tuichat_utils/tui_elements/server_infotable_message.txt
tuichat/tuichat_utils/tui_elements/server_logo.txt
tuichat-0.6.3.dist-info/METADATA
tuichat-0.6.3.dist-info/WHEEL
tuichat-0.6.3.dist-info/entry_points.txt
tuichat-0.6.3.dist-info/top_level.txt
tuichat-0.6.3.dist-info/RECORD
