Metadata-Version: 2.1
Name: tuichat
Version: 0.6.3
Summary: A simple messaging program and API
Home-page: https://github.com/kukree/tuichat
Author: Evgeny Kuleshov
Author-email: kulevgen32@gmail.com
License: UNKNOWN
Platform: UNKNOWN
Classifier: Programming Language :: Python :: 3.6
Classifier: License :: OSI Approved :: GNU General Public License v3 (GPLv3)
Classifier: Environment :: Console
Classifier: Operating System :: OS Independent
Classifier: Topic :: Communications :: Chat
Requires-Dist: importlib.resources
Requires-Dist: tqdm
